CLASSIFIERS
HISTORY.rst
LICENSE.txt
MANIFEST.in
README.rst
setup.cfg
setup.py
versioneer.py
doc/Makefile
doc/source/conf.py
doc/source/index.rst
doc/source/_static/count.png
requirements/ci.txt
requirements/daemon.txt
requirements/main.txt
requirements/redis.txt
requirements/riak.txt
requirements/test.txt
sifr/__init__.py
sifr/_version.py
sifr/hll.py
sifr/span.py
sifr/storage.py
sifr/util.py
sifr/version.py
sifr.egg-info/PKG-INFO
sifr.egg-info/SOURCES.txt
sifr.egg-info/dependency_links.txt
sifr.egg-info/entry_points.txt
sifr.egg-info/not-zip-safe
sifr.egg-info/requires.txt
sifr.egg-info/top_level.txt
sifr/backports/__init__.py
sifr/backports/counter.py
sifr/backports/total_ordering.py
sifr/daemon/__init__.py
sifr/daemon/__main__.py
sifr/daemon/msgpack.py
sifr/daemon/ws.py